{"url":"https:\/\/crm.agrachoff.ru\/rest\/29\/sex0vh7wpi4jv53r\/task.checklistitem.getlist.json","info":{"url":"https:\/\/crm.agrachoff.ru\/rest\/29\/sex0vh7wpi4jv53r\/task.checklistitem.getlist.json","content_type":"application\/json; charset=utf-8","http_code":200,"header_size":624,"request_size":216,"filetime":-1,"ssl_verify_result":0,"redirect_count":0,"total_time":0.261747,"namelookup_time":0.000612,"connect_time":0.03619,"pretransfer_time":0.098935,"size_upload":12,"size_download":221,"speed_download":844,"speed_upload":45,"download_content_length":221,"upload_content_length":12,"starttransfer_time":0.098939,"redirect_time":0,"redirect_url":"","primary_ip":"188.68.204.227","certinfo":[],"primary_port":443,"local_ip":"192.168.31.252","local_port":57624,"http_version":3,"protocol":2,"ssl_verifyresult":0,"scheme":"HTTPS","appconnect_time_us":98880,"connect_time_us":36190,"namelookup_time_us":612,"pretransfer_time_us":98935,"redirect_time_us":0,"starttransfer_time_us":98939,"total_time_us":261747},"params":{"method":"task.checklistitem.getlist","params":{"taskId":"13581"}},"result":{"result":[],"time":{"start":1729512192.710206,"finish":1729512192.80387,"duration":0.09366393089294434,"processing":0.06040811538696289,"date_start":"2024-10-21T15:03:12+03:00","date_finish":"2024-10-21T15:03:12+03:00"}}}